bunches-0.1.3.dist-info/METADATA
bunches-0.1.3.dist-info/WHEEL
bunches-0.1.3.dist-info/licenses/LICENSE
bunches/__init__.py
bunches/base.py
bunches/kinds.py
bunches/mappings.py
bunches/sequences.py
bunches/settings.py
bunches/utilities.py
bunches-0.1.3.dist-info/RECORD
