Metadata-Version: 2.1
Name: bunches
Version: 0.1.3
Summary: Drop-in replacements for Python collections
Author-Email: Corey Rayburn Yung <coreyrayburnyung@gmail.com>
License: Apache Software License 2.0
Classifier: Development Status :: 4 - Beta
Classifier: Intended Audience :: Developers
Classifier: Programming Language :: Python
Classifier: Programming Language :: Python :: 3
Classifier: Programming Language :: Python :: 3 :: Only
Classifier: Programming Language :: Python :: 3.11
Classifier: Programming Language :: Python :: 3.12
Classifier: Topic :: Software Development
Project-URL: Documentation, https://WithPrecedent.github.io/bunches
Project-URL: Repository, https://github.com/WithPrecedent/bunches
Project-URL: Issues, https://github.com/WithPrecedent/bunches/issues
Project-URL: Changelog, https://WithPrecedent.github.io/bunches/changelog
Requires-Python: >=3.11
